build_dependencies/__init__.py
build_dependencies/get_efselab.py
build_dependencies/install.sh
build_dependencies/install_pandoc.py
build_dependencies/install_udpipe.py
build_dependencies/tools_conf.py
build_dependencies/en/__init__.py
build_dependencies/en/en/__init__.py
build_dependencies/en/en/english-ud-2.0-170801.udpipe
build_dependencies/en/histnorm/__init__.py
build_dependencies/en/histnorm/bnc.mono.en.freqs
build_dependencies/en/histnorm/engGramp2.py
build_dependencies/sv/__init__.py
build_dependencies/sv/swe-pipeline-ud2.tar.gz
build_dependencies/sv/HistNorm/__init__.py
build_dependencies/sv/HistNorm/resources/__init__.py
build_dependencies/sv/HistNorm/resources/swedish/__init__.py
resources/__init__.py
resources/corpus/__init__.py
resources/corpus/annotated/__init__.py
resources/corpus/raw/__init__.py
resources/scripts/__init__.py
resources/scripts/initial.py
server/__init__.py
server/config.py
server/lib/__init__.py
server/lib/download.py
server/lib/exceptions.py
server/lib/fetch_current_sentences.py
server/lib/fetch_data.py
server/lib/fetch_features.py
server/lib/fetch_frequencies.py
server/lib/fetch_lengths.py
server/lib/load_data.py
server/lib/utils.py
server/models/__init__.py
server/models/text.py
server/models/user.py
server/routers/__init__.py
server/routers/database.py
server/routers/download.py
server/routers/favicon.py
server/routers/features.py
server/routers/frequencies.py
server/routers/lengths.py
server/routers/states.py
server/routers/text.py
server/routers/texts.py
swegram_main/__init__.py
swegram_main/config.py
swegram_main/version.py
swegram_main/data/__init__.py
swegram_main/data/features.py
swegram_main/data/metadata.py
swegram_main/data/paragraphs.py
swegram_main/data/sentences.py
swegram_main/data/texts.py
swegram_main/data/tokens.py
swegram_main/handler/__init__.py
swegram_main/handler/build.py
swegram_main/handler/cli.py
swegram_main/handler/handler.py
swegram_main/handler/parser.py
swegram_main/handler/visualization.py
swegram-2.1.5.dist-info/LICENSE.md
swegram-2.1.5.dist-info/METADATA
swegram-2.1.5.dist-info/WHEEL
swegram-2.1.5.dist-info/entry_points.txt
swegram-2.1.5.dist-info/top_level.txt
swegram-2.1.5.dist-info/RECORD
