Metadata-Version: 2.1
Name: swegram
Version: 2.1.5
Summary: CLI library for Swegram
Home-page: https://github.com/bmegyesi/swegram-v2
Author: Rex Ruan
License: # MIT License
Requires-Dist: apscheduler
Requires-Dist: cryptography
Requires-Dist: Cython
Requires-Dist: databases[mysql]
Requires-Dist: fastapi
Requires-Dist: gunicorn
Requires-Dist: jellyfish
Requires-Dist: mysql-connector-python
Requires-Dist: mysqlclient
Requires-Dist: openpyxl
Requires-Dist: pandas
Requires-Dist: python-Levenshtein
Requires-Dist: requests
Requires-Dist: uvicorn
